mosaik_zmq.py
mosaik_zmq-0.1.1.dist-info/DESCRIPTION.rst
mosaik_zmq-0.1.1.dist-info/METADATA
mosaik_zmq-0.1.1.dist-info/RECORD
mosaik_zmq-0.1.1.dist-info/WHEEL
mosaik_zmq-0.1.1.dist-info/entry_points.txt
mosaik_zmq-0.1.1.dist-info/metadata.json
mosaik_zmq-0.1.1.dist-info/top_level.txt
