Metadata-Version: 2.0
Name: mosaik-zmq
Version: 0.1.1
Summary: Sends mosaik simulation data to ZeroMQ socket.
Home-page: https://bitbucket.org/mosaik/mosaik-zmq
Author: Jan Soeren Schwarz
Author-email: schwarz at offis.de
License: UNKNOWN
Platform: UNKNOWN
Classifier: Development Status :: 4 - Beta
Classifier: Environment :: Console
Classifier: Intended Audience :: Science/Research
Classifier: License :: OSI Approved :: GNU Lesser General Public License v2 (LGPLv2)
Classifier: Natural Language :: English
Classifier: Operating System :: OS Independent
Classifier: Programming Language :: Python
Classifier: Programming Language :: Python :: 3
Classifier: Programming Language :: Python :: 3.3
Classifier: Programming Language :: Python :: 3.4
Classifier: Topic :: Scientific/Engineering
Requires-Dist: mosaik (>=2.1)
Requires-Dist: mosaik-api (>=2.1)
Requires-Dist: pyzmq (>=15.1.0)
